{"id":1031308,"name":"Bentley System Inc","transferAgent":null,"allClaimedTransferAgents":[{"dtcMemberId":7807,"name":" COMPUTERSHARE TRUST COMPANY, N.A./DRS                                 ","asOfDate":{"value":"2022-04-14"},"docUrl":"https://www.sec.gov/Archives/edgar/data/1031308/000110465922046039/tm223662-1_def14a.htm"},{"dtcMemberId":null,"name":"Computershare Inc.","asOfDate":{"value":"2020-12-17"},"docUrl":"https://www.nasdaqtrader.com/content/home/help/samplereports/Fundamental_Data_cusip121720.xlsx"}],"tickers":[{"ticker":"BSY","exchange":"Nasdaq","description":"Class B Common Stock","hasOnlinePurchase":null,"cusip":"08265T208"}],"holders":{"filingDate":{"value":"2022-03-01"},"totalHolders":2952,"docUrls":["1031308/000162828022004474/bsy-20211231.htm"]}}