{"id":1040470,"name":"Aehr Test Systems","transferAgent":null,"allClaimedTransferAgents":[{"dtcMemberId":7807,"name":" COMPUTERSHARE TRUST COMPANY, N.A./DRS                                 ","asOfDate":{"value":"2022-09-23"},"docUrl":"https://www.sec.gov/Archives/edgar/data/1040470/000165495422012880/aehr_def14a.htm"},{"dtcMemberId":null,"name":"U.S. Stock Transfer Corporation","asOfDate":{"value":"2020-12-17"},"docUrl":"https://www.nasdaqtrader.com/content/home/help/samplereports/Fundamental_Data_cusip121720.xlsx"}],"tickers":[{"ticker":"AEHR","exchange":"Nasdaq","description":"Common Stock","hasOnlinePurchase":null,"cusip":"00760J108"}],"holders":{"filingDate":{"value":"2022-08-26"},"totalHolders":106,"docUrls":["1040470/000165495422011877/aehr_10k.htm"]}}