{"id":1075736,"name":"Crexendo Inc","transferAgent":{"dtcMemberId":7922,"name":"Direct Transfer LLC."},"allClaimedTransferAgents":[{"dtcMemberId":7922,"name":"Direct Transfer LLC.","asOfDate":{"value":"2020-12-17"},"docUrl":"https://www.nasdaqtrader.com/content/home/help/samplereports/Fundamental_Data_cusip121720.xlsx"}],"tickers":[{"ticker":"CXDO","exchange":"Nasdaq","description":"Common Stock","hasOnlinePurchase":null,"cusip":"226552107"}],"holders":{"filingDate":{"value":"2022-03-21"},"totalHolders":197,"docUrls":["1075736/000165495422003516/cxdo_10k.htm"]}}