{"id":109198,"name":"The TJX Companies, Inc.","transferAgent":{"dtcMemberId":7807,"name":"COMPUTERSHARE TRUST COMPANY, N.A."},"allClaimedTransferAgents":[{"dtcMemberId":7807,"name":"COMPUTERSHARE TRUST COMPANY, N.A.","asOfDate":{"value":"1900-01-01"},"docUrl":"https://docs.google.com/spreadsheets/d/1MjDad_gZmywTxMVQxsnH2uc9sPIvUa3O51SDyTYm_vs/edit"}],"tickers":[{"ticker":"TJX","exchange":"NYSE","description":"Common Stock","hasOnlinePurchase":"No","cusip":"872540109"}],"holders":{"filingDate":{"value":"2022-03-30"},"totalHolders":1984,"docUrls":["109198/000010919822000008/tjx-20220129.htm"]}}