{"id":1095073,"name":"Everest Re Group, Ltd.","transferAgent":{"dtcMemberId":7807,"name":" COMPUTERSHARE TRUST COMPANY, N.A./DRS                                 "},"allClaimedTransferAgents":[{"dtcMemberId":7807,"name":" COMPUTERSHARE TRUST COMPANY, N.A./DRS                                 ","asOfDate":{"value":"2022-04-08"},"docUrl":"https://www.sec.gov/Archives/edgar/data/1095073/000109507322000007/proxy2022.htm"}],"tickers":[{"ticker":"RE","exchange":"NYSE","description":"Common Stock","hasOnlinePurchase":null,"cusip":"G3223R108"}],"holders":{"filingDate":{"value":"2022-02-28"},"totalHolders":630,"docUrls":["1095073/000109507322000005/re-20211231.htm"]}}