{"id":1559998,"name":"Gaucho Group Holdings Inc","transferAgent":{"dtcMemberId":7808,"name":" CONTINENTAL STOCK TRANSFER & TRUST COMPANY/DRS                        "},"allClaimedTransferAgents":[{"dtcMemberId":7808,"name":" CONTINENTAL STOCK TRANSFER & TRUST COMPANY/DRS                        ","asOfDate":{"value":"2022-11-09"},"docUrl":"https://www.sec.gov/Archives/edgar/data/1559998/000149315222031025/formdef14a.htm"},{"dtcMemberId":7808,"name":" CONTINENTAL STOCK TRANSFER & TRUST COMPANY/DRS                        ","asOfDate":{"value":"2022-07-21"},"docUrl":"https://www.sec.gov/Archives/edgar/data/1559998/000149315222019972/formdef14a.htm"}],"tickers":[{"ticker":"VINO","exchange":"Nasdaq","description":null,"hasOnlinePurchase":null,"cusip":"36809R206"}],"holders":{"filingDate":{"value":"2022-05-19"},"totalHolders":1505,"docUrls":["1559998/000149315222014481/form10-ka.htm","1559998/000149315222014482/form10-ka.htm"]}}