{"id":1581804,"name":"Navigator Holdings Ltd.","transferAgent":{"dtcMemberId":null,"name":"AMERICAN STOCK TRANSFER & TRUST COMPANY, LLC"},"allClaimedTransferAgents":[{"dtcMemberId":null,"name":"AMERICAN STOCK TRANSFER & TRUST COMPANY, LLC","asOfDate":{"value":"1900-01-01"},"docUrl":"https://docs.google.com/spreadsheets/d/1MjDad_gZmywTxMVQxsnH2uc9sPIvUa3O51SDyTYm_vs/edit"}],"tickers":[{"ticker":"NVGS","exchange":"NYSE","description":"Common Stock","hasOnlinePurchase":"Yes","cusip":"Y62132108"}],"holders":{"filingDate":null,"totalHolders":null,"docUrls":[]}}