{"id":1672688,"name":"Absci Corp","transferAgent":{"dtcMemberId":7807,"name":"COMPUTERSHARE TRUST COMPANY, N.A."},"allClaimedTransferAgents":[{"dtcMemberId":7807,"name":"COMPUTERSHARE TRUST COMPANY, N.A.","asOfDate":{"value":"1900-01-01"},"docUrl":"https://docs.google.com/spreadsheets/d/1MjDad_gZmywTxMVQxsnH2uc9sPIvUa3O51SDyTYm_vs/edit"}],"tickers":[{"ticker":"ABSI","exchange":"Nasdaq","description":null,"hasOnlinePurchase":"No","cusip":"9.1E+110"}],"holders":{"filingDate":{"value":"2022-03-22"},"totalHolders":6989,"docUrls":["1672688/000162828022006925/absi-20211231.htm"]}}