{"id":1711012,"name":"Senmiao Technology Ltd","transferAgent":{"dtcMemberId":7924,"name":"VStock Transfer LLC"},"allClaimedTransferAgents":[{"dtcMemberId":7924,"name":"VStock Transfer LLC","asOfDate":{"value":"2020-12-17"},"docUrl":"https://www.nasdaqtrader.com/content/home/help/samplereports/Fundamental_Data_cusip121720.xlsx"}],"tickers":[{"ticker":"AIHS","exchange":"Nasdaq","description":"Common Stock","hasOnlinePurchase":null,"cusip":"817225105"}],"holders":{"filingDate":{"value":"2022-07-15"},"totalHolders":28,"docUrls":["1711012/000141057822001945/aihs-20220331x10k.htm"]}}