{"id":1737927,"name":"Canopy Growth Corp","transferAgent":{"dtcMemberId":null,"name":"Computershare Investor Services Inc."},"allClaimedTransferAgents":[{"dtcMemberId":null,"name":"Computershare Investor Services Inc.","asOfDate":{"value":"2020-12-17"},"docUrl":"https://www.nasdaqtrader.com/content/home/help/samplereports/Fundamental_Data_cusip121720.xlsx"}],"tickers":[{"ticker":"CGC","exchange":"Nasdaq","description":"Common Shares","hasOnlinePurchase":null,"cusip":"138035100"}],"holders":{"filingDate":{"value":"2022-05-31"},"totalHolders":492,"docUrls":["1737927/000156459022021923/cgc-10k_20220331.htm"]}}