{"id":1830795,"name":"Quantum FinTech Acquisition Corp","transferAgent":{"dtcMemberId":7808,"name":" CONTINENTAL STOCK TRANSFER & TRUST COMPANY/DRS                        "},"allClaimedTransferAgents":[{"dtcMemberId":7808,"name":" CONTINENTAL STOCK TRANSFER & TRUST COMPANY/DRS                        ","asOfDate":{"value":"2023-01-17"},"docUrl":"https://www.sec.gov/Archives/edgar/data/1830795/000121390023003035/def14a0123_quantumfin.htm"},{"dtcMemberId":7808,"name":" CONTINENTAL STOCK TRANSFER & TRUST COMPANY/DRS                        ","asOfDate":{"value":"2023-01-17"},"docUrl":"https://www.sec.gov/Archives/edgar/data/1830795/000121390023003035/def14a0123_quantumfin.htm"}],"tickers":[{"ticker":"QFTA","exchange":"NYSE","description":"Common Stock","hasOnlinePurchase":null,"cusip":"74767A105"},{"ticker":"QFTA-UN","exchange":"NYSE","description":null,"hasOnlinePurchase":null,"cusip":null}],"holders":{"filingDate":{"value":"2022-04-11"},"totalHolders":14,"docUrls":["1830795/000121390022019074/f10k2021a1_quantumfin.htm"]}}