{"id":352955,"name":"CKX Lands Inc","transferAgent":{"dtcMemberId":7807,"name":"COMPUTERSHARE TRUST COMPANY, N.A."},"allClaimedTransferAgents":[{"dtcMemberId":7807,"name":"COMPUTERSHARE TRUST COMPANY, N.A.","asOfDate":{"value":"1900-01-01"},"docUrl":"https://docs.google.com/spreadsheets/d/1MjDad_gZmywTxMVQxsnH2uc9sPIvUa3O51SDyTYm_vs/edit"}],"tickers":[{"ticker":"CKX","exchange":"NYSE","description":"Common Stock","hasOnlinePurchase":"Yes","cusip":"12562N104"}],"holders":{"filingDate":{"value":"2022-03-28"},"totalHolders":325,"docUrls":["352955/000143774922007344/ckx20211231_10k.htm"]}}