{"id":738214,"name":"Aemetis Inc","transferAgent":null,"allClaimedTransferAgents":[{"dtcMemberId":7806,"name":" EQUINITI TRUST COMPANY/DRS                                            ","asOfDate":{"value":"2022-04-06"},"docUrl":"https://www.sec.gov/Archives/edgar/data/738214/000165495422004643/amts_def14a.htm"},{"dtcMemberId":null,"name":"Corporate Stock Transfer, Inc.","asOfDate":{"value":"2020-12-17"},"docUrl":"https://www.nasdaqtrader.com/content/home/help/samplereports/Fundamental_Data_cusip121720.xlsx"}],"tickers":[{"ticker":"AMTX","exchange":"Nasdaq","description":"Common Stock","hasOnlinePurchase":null,"cusip":"00770K202"}],"holders":{"filingDate":{"value":"2022-03-10"},"totalHolders":173,"docUrls":["738214/000165495422002831/amts_10k.htm"]}}