{"id":791908,"name":"XOMA Corp","transferAgent":null,"allClaimedTransferAgents":[{"dtcMemberId":null,"name":"First Interstate Bank of California","asOfDate":{"value":"2020-12-17"},"docUrl":"https://www.nasdaqtrader.com/content/home/help/samplereports/Fundamental_Data_cusip121720.xlsx"},{"dtcMemberId":null,"name":"EQ Shareowner Services","asOfDate":{"value":"2020-12-17"},"docUrl":"https://www.nasdaqtrader.com/content/home/help/samplereports/Fundamental_Data_cusip121720.xlsx"},{"dtcMemberId":null,"name":"AMERICAN STOCK TRANSFER & TRUST COMPANY, LLC","asOfDate":{"value":"1900-01-01"},"docUrl":"https://docs.google.com/spreadsheets/d/1MjDad_gZmywTxMVQxsnH2uc9sPIvUa3O51SDyTYm_vs/edit"},{"dtcMemberId":7805,"name":"American Stock Transfer & Trust Company","asOfDate":{"value":"2020-12-17"},"docUrl":"https://www.nasdaqtrader.com/content/home/help/samplereports/Fundamental_Data_cusip121720.xlsx"},{"dtcMemberId":null,"name":"AMERICAN STOCK TRANSFER & TRUST COMPANY, LLC","asOfDate":{"value":"1900-01-01"},"docUrl":"https://docs.google.com/spreadsheets/d/1MjDad_gZmywTxMVQxsnH2uc9sPIvUa3O51SDyTYm_vs/edit"}],"tickers":[{"ticker":"XOMAO","exchange":"Nasdaq","description":null,"hasOnlinePurchase":null,"cusip":"98419J404"},{"ticker":"XOMA","exchange":"Nasdaq","description":"Common Stock","hasOnlinePurchase":"Yes","cusip":"98419J206"},{"ticker":"XOMAP","exchange":"Nasdaq","description":"8.625% Series A Cumulative Perpetual Preferred Stock","hasOnlinePurchase":null,"cusip":"98419J305"}],"holders":{"filingDate":{"value":"2022-03-08"},"totalHolders":196,"docUrls":["791908/000155837022003022/tmb-20211231x10k.htm"]}}