{"id":823277,"name":"CHS Inc","transferAgent":null,"allClaimedTransferAgents":[{"dtcMemberId":null,"name":"EQ Shareowner Services","asOfDate":{"value":"2020-12-17"},"docUrl":"https://www.nasdaqtrader.com/content/home/help/samplereports/Fundamental_Data_cusip121720.xlsx"},{"dtcMemberId":null,"name":"EQ Shareowner Services","asOfDate":{"value":"2020-12-17"},"docUrl":"https://www.nasdaqtrader.com/content/home/help/samplereports/Fundamental_Data_cusip121720.xlsx"},{"dtcMemberId":null,"name":"EQ Shareowner Services","asOfDate":{"value":"2020-12-17"},"docUrl":"https://www.nasdaqtrader.com/content/home/help/samplereports/Fundamental_Data_cusip121720.xlsx"},{"dtcMemberId":null,"name":"EQUINITI TRUST COMPANY","asOfDate":{"value":"1900-01-01"},"docUrl":"https://docs.google.com/spreadsheets/d/1MjDad_gZmywTxMVQxsnH2uc9sPIvUa3O51SDyTYm_vs/edit"},{"dtcMemberId":null,"name":"EQ Shareowner Services","asOfDate":{"value":"2020-12-17"},"docUrl":"https://www.nasdaqtrader.com/content/home/help/samplereports/Fundamental_Data_cusip121720.xlsx"},{"dtcMemberId":null,"name":"EQUINITI TRUST COMPANY","asOfDate":{"value":"1900-01-01"},"docUrl":"https://docs.google.com/spreadsheets/d/1MjDad_gZmywTxMVQxsnH2uc9sPIvUa3O51SDyTYm_vs/edit"},{"dtcMemberId":null,"name":"Wells Fargo Shareholder Services","asOfDate":{"value":"2020-12-17"},"docUrl":"https://www.nasdaqtrader.com/content/home/help/samplereports/Fundamental_Data_cusip121720.xlsx"},{"dtcMemberId":null,"name":"EQUINITI TRUST COMPANY","asOfDate":{"value":"1900-01-01"},"docUrl":"https://docs.google.com/spreadsheets/d/1MjDad_gZmywTxMVQxsnH2uc9sPIvUa3O51SDyTYm_vs/edit"}],"tickers":[{"ticker":"CHSCN","exchange":"Nasdaq","description":"Preferred Class B Series 2 Reset Rate","hasOnlinePurchase":null,"cusip":"12542R506"},{"ticker":"CHSCL","exchange":"Nasdaq","description":"Class B Cumulative Redeemable Preferred Stock, Series 4","hasOnlinePurchase":null,"cusip":"12542R803"},{"ticker":"CHSCM","exchange":"Nasdaq","description":"Class B Reset Rate Cumulative Redeemable Preferred Stock, Series 3","hasOnlinePurchase":"Yes","cusip":"12542R704"},{"ticker":"CHSCO","exchange":"Nasdaq","description":"Class B Cumulative Redeemable Preferred Stock","hasOnlinePurchase":"Yes","cusip":"12542R308"},{"ticker":"CHSCP","exchange":"Nasdaq","description":"8%  Cumulative Redeemable Preferred Stock","hasOnlinePurchase":"Yes","cusip":"12542R209"}],"holders":{"filingDate":null,"totalHolders":null,"docUrls":[]}}