{"id":886982,"name":"GOLDMAN SACHS GROUP INC","transferAgent":{"dtcMemberId":7807,"name":" COMPUTERSHARE TRUST COMPANY, N.A./DRS                                 "},"allClaimedTransferAgents":[{"dtcMemberId":7807,"name":" COMPUTERSHARE TRUST COMPANY, N.A./DRS                                 ","asOfDate":{"value":"2022-03-18"},"docUrl":"https://www.sec.gov/Archives/edgar/data/886982/000119312522079120/d62428ddef14a.htm"},{"dtcMemberId":7807,"name":"COMPUTERSHARE TRUST COMPANY, N.A.","asOfDate":{"value":"1900-01-01"},"docUrl":"https://docs.google.com/spreadsheets/d/1MjDad_gZmywTxMVQxsnH2uc9sPIvUa3O51SDyTYm_vs/edit"},{"dtcMemberId":7807,"name":" COMPUTERSHARE TRUST COMPANY, N.A./DRS                                 ","asOfDate":{"value":"2022-03-18"},"docUrl":"https://www.sec.gov/Archives/edgar/data/886982/000119312522079120/d62428ddef14a.htm"},{"dtcMemberId":7807,"name":"COMPUTERSHARE TRUST COMPANY, N.A.","asOfDate":{"value":"1900-01-01"},"docUrl":"https://docs.google.com/spreadsheets/d/1MjDad_gZmywTxMVQxsnH2uc9sPIvUa3O51SDyTYm_vs/edit"},{"dtcMemberId":7807,"name":" COMPUTERSHARE TRUST COMPANY, N.A./DRS                                 ","asOfDate":{"value":"2022-03-18"},"docUrl":"https://www.sec.gov/Archives/edgar/data/886982/000119312522079120/d62428ddef14a.htm"},{"dtcMemberId":7807,"name":"COMPUTERSHARE TRUST COMPANY, N.A.","asOfDate":{"value":"1900-01-01"},"docUrl":"https://docs.google.com/spreadsheets/d/1MjDad_gZmywTxMVQxsnH2uc9sPIvUa3O51SDyTYm_vs/edit"},{"dtcMemberId":7807,"name":" COMPUTERSHARE TRUST COMPANY, N.A./DRS                                 ","asOfDate":{"value":"2022-03-18"},"docUrl":"https://www.sec.gov/Archives/edgar/data/886982/000119312522079120/d62428ddef14a.htm"},{"dtcMemberId":7807,"name":"COMPUTERSHARE TRUST COMPANY, N.A.","asOfDate":{"value":"1900-01-01"},"docUrl":"https://docs.google.com/spreadsheets/d/1MjDad_gZmywTxMVQxsnH2uc9sPIvUa3O51SDyTYm_vs/edit"},{"dtcMemberId":7807,"name":" COMPUTERSHARE TRUST COMPANY, N.A./DRS                                 ","asOfDate":{"value":"2022-03-18"},"docUrl":"https://www.sec.gov/Archives/edgar/data/886982/000119312522079120/d62428ddef14a.htm"},{"dtcMemberId":7807,"name":"COMPUTERSHARE TRUST COMPANY, N.A.","asOfDate":{"value":"1900-01-01"},"docUrl":"https://docs.google.com/spreadsheets/d/1MjDad_gZmywTxMVQxsnH2uc9sPIvUa3O51SDyTYm_vs/edit"},{"dtcMemberId":7807,"name":" COMPUTERSHARE TRUST COMPANY, N.A./DRS                                 ","asOfDate":{"value":"2022-03-18"},"docUrl":"https://www.sec.gov/Archives/edgar/data/886982/000119312522079120/d62428ddef14a.htm"},{"dtcMemberId":7807,"name":"COMPUTERSHARE TRUST COMPANY, N.A.","asOfDate":{"value":"1900-01-01"},"docUrl":"https://docs.google.com/spreadsheets/d/1MjDad_gZmywTxMVQxsnH2uc9sPIvUa3O51SDyTYm_vs/edit"}],"tickers":[{"ticker":"GS-PA","exchange":"NYSE","description":null,"hasOnlinePurchase":"No","cusip":null},{"ticker":"GS-PC","exchange":"NYSE","description":null,"hasOnlinePurchase":"No","cusip":null},{"ticker":"GS","exchange":"NYSE","description":"Common Stock","hasOnlinePurchase":"No","cusip":"38141G104"},{"ticker":"GS-PK","exchange":"NYSE","description":null,"hasOnlinePurchase":"No","cusip":null},{"ticker":"GS-PD","exchange":"NYSE","description":null,"hasOnlinePurchase":"No","cusip":null},{"ticker":"GS-PJ","exchange":"NYSE","description":null,"hasOnlinePurchase":"No","cusip":null}],"holders":{"filingDate":{"value":"2022-02-25"},"totalHolders":5963,"docUrls":["886982/000119312522052682/d192225d10k.htm"]}}