{"id":921299,"name":"FibroGen Inc","transferAgent":null,"allClaimedTransferAgents":[{"dtcMemberId":7805,"name":" AMERICAN STOCK TRANSFER & TRUST COMPANY, LLC/DRS                      ","asOfDate":{"value":"2022-04-29"},"docUrl":"https://www.sec.gov/Archives/edgar/data/921299/000156459022016537/fgen-def14a_20220616.htm"},{"dtcMemberId":null,"name":"EQ Shareowner Services","asOfDate":{"value":"2020-12-17"},"docUrl":"https://www.nasdaqtrader.com/content/home/help/samplereports/Fundamental_Data_cusip121720.xlsx"},{"dtcMemberId":null,"name":"AMERICAN STOCK TRANSFER & TRUST COMPANY, LLC","asOfDate":{"value":"1900-01-01"},"docUrl":"https://docs.google.com/spreadsheets/d/1MjDad_gZmywTxMVQxsnH2uc9sPIvUa3O51SDyTYm_vs/edit"}],"tickers":[{"ticker":"FGEN","exchange":"Nasdaq","description":"Common Stock","hasOnlinePurchase":"Yes","cusip":"31572Q808"}],"holders":{"filingDate":{"value":"2022-02-28"},"totalHolders":118,"docUrls":["921299/000156459022007632/fgen-10k_20211231.htm"]}}