{"id":93410,"name":"Chevron Corporation","transferAgent":{"dtcMemberId":7807,"name":" COMPUTERSHARE TRUST COMPANY, N.A./DRS                                 "},"allClaimedTransferAgents":[{"dtcMemberId":7807,"name":" COMPUTERSHARE TRUST COMPANY, N.A./DRS                                 ","asOfDate":{"value":"2022-04-07"},"docUrl":"https://www.sec.gov/Archives/edgar/data/93410/000119312522098301/d292137ddef14a.htm"},{"dtcMemberId":7807,"name":"COMPUTERSHARE TRUST COMPANY, N.A.","asOfDate":{"value":"1900-01-01"},"docUrl":"https://docs.google.com/spreadsheets/d/1MjDad_gZmywTxMVQxsnH2uc9sPIvUa3O51SDyTYm_vs/edit"}],"tickers":[{"ticker":"CVX","exchange":"NYSE","description":"Common Stock","hasOnlinePurchase":"Yes","cusip":"166764100"}],"holders":{"filingDate":{"value":"2022-02-24"},"totalHolders":109000,"docUrls":["93410/000009341022000019/cvx-20211231.htm"]}}