{"id":946647,"name":"Premier Financial Corp","transferAgent":{"dtcMemberId":null,"name":"Computershare Limited"},"allClaimedTransferAgents":[{"dtcMemberId":null,"name":"Computershare Limited","asOfDate":{"value":"2020-12-17"},"docUrl":"https://www.nasdaqtrader.com/content/home/help/samplereports/Fundamental_Data_cusip121720.xlsx"}],"tickers":[{"ticker":"PFC","exchange":"Nasdaq","description":"Common Stock","hasOnlinePurchase":null,"cusip":"74052F108"}],"holders":{"filingDate":{"value":"2022-03-01"},"totalHolders":6820,"docUrls":["946647/000095017022002441/pfc-20211231.htm"]}}