{"id":"1039399-FORM","ticker":"FORM","cusip":"346375108","issuer":"FormFactor Inc","issuerId":1039399,"latestClaimedTransferAgent":{"dtcMemberId":7807,"name":" COMPUTERSHARE TRUST COMPANY, N.A./DRS                                 ","asOfDate":{"value":"2022-04-13"},"docUrl":"https://www.sec.gov/Archives/edgar/data/1039399/000114036122014333/ny20001965x2_def14a.htm"},"allClaimedTransferAgents":[{"dtcMemberId":7807,"name":" COMPUTERSHARE TRUST COMPANY, N.A./DRS                                 ","asOfDate":{"value":"2022-04-13"},"docUrl":"https://www.sec.gov/Archives/edgar/data/1039399/000114036122014333/ny20001965x2_def14a.htm"},{"dtcMemberId":null,"name":"Equiserve Trust Company, N.A.","asOfDate":{"value":"2020-12-17"},"docUrl":"https://www.nasdaqtrader.com/content/home/help/samplereports/Fundamental_Data_cusip121720.xlsx"}]}