{"id":"1061219-EPD","ticker":"EPD","cusip":"293792107","issuer":"Enterprise Products Partners L.P.","issuerId":1061219,"latestClaimedTransferAgent":{"dtcMemberId":null,"name":"EQUINITI TRUST COMPANY","asOfDate":{"value":"1900-01-01"},"docUrl":"https://docs.google.com/spreadsheets/d/1MjDad_gZmywTxMVQxsnH2uc9sPIvUa3O51SDyTYm_vs/edit"},"allClaimedTransferAgents":[{"dtcMemberId":null,"name":"EQUINITI TRUST COMPANY","asOfDate":{"value":"1900-01-01"},"docUrl":"https://docs.google.com/spreadsheets/d/1MjDad_gZmywTxMVQxsnH2uc9sPIvUa3O51SDyTYm_vs/edit"}]}