{"id":"1113423-AEZS","ticker":"AEZS","cusip":"7975402","issuer":"AEterna Zentaris Inc","issuerId":1113423,"latestClaimedTransferAgent":{"dtcMemberId":null,"name":"National Bank Trust, Inc.","asOfDate":{"value":"2020-12-17"},"docUrl":"https://www.nasdaqtrader.com/content/home/help/samplereports/Fundamental_Data_cusip121720.xlsx"},"allClaimedTransferAgents":[{"dtcMemberId":null,"name":"National Bank Trust, Inc.","asOfDate":{"value":"2020-12-17"},"docUrl":"https://www.nasdaqtrader.com/content/home/help/samplereports/Fundamental_Data_cusip121720.xlsx"}]}