{"id":"1235468-LQDT","ticker":"LQDT","cusip":"53635B107","issuer":"Liquidity Services Inc","issuerId":1235468,"latestClaimedTransferAgent":{"dtcMemberId":7807,"name":" COMPUTERSHARE TRUST COMPANY, N.A./DRS                                 ","asOfDate":{"value":"2023-01-24"},"docUrl":"https://www.sec.gov/Archives/edgar/data/1235468/000095017023001082/lqdt-definitive_proxy.htm"},"allClaimedTransferAgents":[{"dtcMemberId":7807,"name":" COMPUTERSHARE TRUST COMPANY, N.A./DRS                                 ","asOfDate":{"value":"2023-01-24"},"docUrl":"https://www.sec.gov/Archives/edgar/data/1235468/000095017023001082/lqdt-definitive_proxy.htm"},{"dtcMemberId":7807,"name":" COMPUTERSHARE TRUST COMPANY, N.A./DRS                                 ","asOfDate":{"value":"2022-01-24"},"docUrl":"https://www.sec.gov/Archives/edgar/data/1235468/000110465922006897/tm223064-1_def14a.htm"},{"dtcMemberId":7807,"name":"Computershare Trust","asOfDate":{"value":"2020-12-17"},"docUrl":"https://www.nasdaqtrader.com/content/home/help/samplereports/Fundamental_Data_cusip121720.xlsx"}]}