{"id":"1274173-JHG","ticker":"JHG","cusip":"G4474Y214","issuer":"Janus Henderson Group plc","issuerId":1274173,"latestClaimedTransferAgent":{"dtcMemberId":7807,"name":" COMPUTERSHARE TRUST COMPANY, N.A./DRS                                 ","asOfDate":{"value":"2022-03-24"},"docUrl":"https://www.sec.gov/Archives/edgar/data/1274173/000130817922000104/ljhg2022_def14a.htm"},"allClaimedTransferAgents":[{"dtcMemberId":7807,"name":" COMPUTERSHARE TRUST COMPANY, N.A./DRS                                 ","asOfDate":{"value":"2022-03-24"},"docUrl":"https://www.sec.gov/Archives/edgar/data/1274173/000130817922000104/ljhg2022_def14a.htm"}]}