{"id":"1579157-VNCE","ticker":"VNCE","cusip":"92719W207","issuer":"Vince Holding Corp.","issuerId":1579157,"latestClaimedTransferAgent":{"dtcMemberId":7824,"name":" BROADRIDGE CORPORATE ISSUER SOLUTIONS INC./DRS                        ","asOfDate":{"value":"2022-04-29"},"docUrl":"https://www.sec.gov/Archives/edgar/data/1579157/000156459022016641/vnce-def14a_20220606.htm"},"allClaimedTransferAgents":[{"dtcMemberId":7824,"name":" BROADRIDGE CORPORATE ISSUER SOLUTIONS INC./DRS                        ","asOfDate":{"value":"2022-04-29"},"docUrl":"https://www.sec.gov/Archives/edgar/data/1579157/000156459022016641/vnce-def14a_20220606.htm"}]}