{"id":"1649739-BAFN","ticker":"BAFN","cusip":"07279B104","issuer":"BAYFIRST FINANCIAL CORP","issuerId":1649739,"latestClaimedTransferAgent":{"dtcMemberId":7808,"name":"CONTINENTAL STOCK TRANSFER & TRUST COMPANY","asOfDate":{"value":"1900-01-01"},"docUrl":"https://docs.google.com/spreadsheets/d/1MjDad_gZmywTxMVQxsnH2uc9sPIvUa3O51SDyTYm_vs/edit"},"allClaimedTransferAgents":[{"dtcMemberId":7808,"name":"CONTINENTAL STOCK TRANSFER & TRUST COMPANY","asOfDate":{"value":"1900-01-01"},"docUrl":"https://docs.google.com/spreadsheets/d/1MjDad_gZmywTxMVQxsnH2uc9sPIvUa3O51SDyTYm_vs/edit"}]}