{"id":"1810560-REVBW","ticker":"REVBW","cusip":"76135L119","issuer":"Revelation Biosciences Inc","issuerId":1810560,"latestClaimedTransferAgent":{"dtcMemberId":7808,"name":" CONTINENTAL STOCK TRANSFER & TRUST COMPANY/DRS                        ","asOfDate":{"value":"2022-12-30"},"docUrl":"https://www.sec.gov/Archives/edgar/data/1810560/000121390022084038/def14a1222_revelationbio.htm"},"allClaimedTransferAgents":[{"dtcMemberId":7808,"name":" CONTINENTAL STOCK TRANSFER & TRUST COMPANY/DRS                        ","asOfDate":{"value":"2022-12-30"},"docUrl":"https://www.sec.gov/Archives/edgar/data/1810560/000121390022084038/def14a1222_revelationbio.htm"}]}