{"id":"1883962-ALOR","ticker":"ALOR","cusip":"G0231L107","issuer":"ALSP Orchid Acquisition Corporation I","issuerId":1883962,"latestClaimedTransferAgent":{"dtcMemberId":7808,"name":" CONTINENTAL STOCK TRANSFER & TRUST COMPANY/DRS                        ","asOfDate":{"value":"2023-02-02"},"docUrl":"https://www.sec.gov/Archives/edgar/data/1883962/000119312523022768/d447085ddef14a.htm"},"allClaimedTransferAgents":[{"dtcMemberId":7808,"name":" CONTINENTAL STOCK TRANSFER & TRUST COMPANY/DRS                        ","asOfDate":{"value":"2023-02-02"},"docUrl":"https://www.sec.gov/Archives/edgar/data/1883962/000119312523022768/d447085ddef14a.htm"}]}