{"id":"742278-RES","ticker":"RES","cusip":"749660106","issuer":"RPC, Inc.","issuerId":742278,"latestClaimedTransferAgent":{"dtcMemberId":null,"name":"AMERICAN STOCK TRANSFER & TRUST COMPANY, LLC","asOfDate":{"value":"1900-01-01"},"docUrl":"https://docs.google.com/spreadsheets/d/1MjDad_gZmywTxMVQxsnH2uc9sPIvUa3O51SDyTYm_vs/edit"},"allClaimedTransferAgents":[{"dtcMemberId":null,"name":"AMERICAN STOCK TRANSFER & TRUST COMPANY, LLC","asOfDate":{"value":"1900-01-01"},"docUrl":"https://docs.google.com/spreadsheets/d/1MjDad_gZmywTxMVQxsnH2uc9sPIvUa3O51SDyTYm_vs/edit"}]}