{"id":"925683-BTO","ticker":"BTO","cusip":"409735206","issuer":"John Hancock Financial Opportunities Fund","issuerId":925683,"latestClaimedTransferAgent":{"dtcMemberId":7807,"name":" COMPUTERSHARE TRUST COMPANY, N.A./DRS                                 ","asOfDate":{"value":"2022-12-15"},"docUrl":"https://www.sec.gov/Archives/edgar/data/925683/000113322822007630/jhfo-html5676_def14a.htm"},"allClaimedTransferAgents":[{"dtcMemberId":7807,"name":" COMPUTERSHARE TRUST COMPANY, N.A./DRS                                 ","asOfDate":{"value":"2022-12-15"},"docUrl":"https://www.sec.gov/Archives/edgar/data/925683/000113322822007630/jhfo-html5676_def14a.htm"},{"dtcMemberId":7807,"name":"COMPUTERSHARE TRUST COMPANY, N.A.","asOfDate":{"value":"1900-01-01"},"docUrl":"https://docs.google.com/spreadsheets/d/1MjDad_gZmywTxMVQxsnH2uc9sPIvUa3O51SDyTYm_vs/edit"}]}