{"id":"943819-RMD","ticker":"RMD","cusip":"761152107","issuer":"RESMED INC","issuerId":943819,"latestClaimedTransferAgent":{"dtcMemberId":7807,"name":" COMPUTERSHARE TRUST COMPANY, N.A./DRS                                 ","asOfDate":{"value":"2022-10-05"},"docUrl":"https://www.sec.gov/Archives/edgar/data/943819/000094381922000014/resmedproxy2022.htm"},"allClaimedTransferAgents":[{"dtcMemberId":7807,"name":" COMPUTERSHARE TRUST COMPANY, N.A./DRS                                 ","asOfDate":{"value":"2022-10-05"},"docUrl":"https://www.sec.gov/Archives/edgar/data/943819/000094381922000014/resmedproxy2022.htm"},{"dtcMemberId":7807,"name":"COMPUTERSHARE TRUST COMPANY, N.A.","asOfDate":{"value":"1900-01-01"},"docUrl":"https://docs.google.com/spreadsheets/d/1MjDad_gZmywTxMVQxsnH2uc9sPIvUa3O51SDyTYm_vs/edit"}]}