{"id":"1464790","name":"B. Riley Financial, Inc.","transferAgent":{},"tickers":[{"exchange":"Nasdaq","ticker":"RILY","cusip":"05580M108"},{"exchange":"Nasdaq","ticker":"RILYG","cusip":"05580M793"},{"exchange":"Nasdaq","ticker":"RILYK","cusip":"05580M827"},{"exchange":"Nasdaq","ticker":"RILYL","cusip":"05580M850"},{"exchange":"Nasdaq","ticker":"RILYM","cusip":"05580M868"},{"exchange":"Nasdaq","ticker":"RILYN","cusip":"05580M801"},{"exchange":"Nasdaq","ticker":"RILYO","cusip":"05580M702"},{"exchange":"Nasdaq","ticker":"RILYP","cusip":"05580M876"},{"exchange":"Nasdaq","ticker":"RILYT","cusip":"05580M835"},{"exchange":"Nasdaq","ticker":"RILYZ","cusip":"05580M819"}],"holders":{"filingDate":"2022-05-06","totalHolders":"119","docUrls":["1464790/000121390022024568/f10k2021a1_brileyfinan.htm"]}}